{
  "formatVersion": "1.1",
  "component": {
    "group": "com.mars.library",
    "module": "toolkit-preference-runtime-base",
    "version": "0.4.2",
    "attributes": {
      "org.gradle.status": "release"
    }
  },
  "createdBy": {
    "gradle": {
      "version": "6.8-20200917220028+0000",
      "buildId": "4jpvimjjorfqpbkx5tfkkvc3ie"
    }
  },
  "variants": [
    {
      "name": "releaseApiPublication",
      "attributes": {
        "org.gradle.category": "library",
        "org.gradle.dependency.bundling": "external",
        "org.gradle.libraryelements": "aar",
        "org.gradle.usage": "java-api"
      },
      "dependencies": [
        {
          "group": "com.mars.library",
          "module": "annotations",
          "version": {
            "requires": "1.0",
            "rejects": [
              "_"
            ]
          }
        },
        {
          "group": "com.mars.library",
          "module": "toolkit-core-android",
          "version": {
            "requires": "0.4.2"
          }
        }
      ],
      "files": [
        {
          "name": "toolkit-preference-runtime-base-0.4.2.aar",
          "url": "toolkit-preference-runtime-base-0.4.2.aar",
          "size": 80825,
          "sha512": "043dce661322d1377a05dc7caebe343b7efc0696129d8062e533e6ae02ad69ebd49c267bb5e7fd02c9fd76a183d1207635f3b9ab140043f3f3427f6dbd803d29",
          "sha256": "41552e5625080c567c5bd0243977fb9894584e91bdab9ca4fb6c98c942d22b88",
          "sha1": "767b8a67c7e94bff048fd0fa512cf7429fa82c99",
          "md5": "9cae510c145d3c55244e3812a4f47c5f"
        }
      ]
    },
    {
      "name": "releaseRuntimePublication",
      "attributes": {
        "org.gradle.category": "library",
        "org.gradle.dependency.bundling": "external",
        "org.gradle.libraryelements": "aar",
        "org.gradle.usage": "java-runtime"
      },
      "dependencies": [
        {
          "group": "com.mars.library",
          "module": "annotations",
          "version": {
            "requires": "1.0",
            "rejects": [
              "_"
            ]
          }
        },
        {
          "group": "com.mars.library",
          "module": "toolkit-core-android",
          "version": {
            "requires": "0.4.2"
          }
        },
        {
          "group": "org.jetbrains.kotlin",
          "module": "kotlin-stdlib-jdk8",
          "version": {
            "requires": "1.4.10",
            "rejects": [
              "_"
            ]
          }
        },
        {
          "group": "org.jetbrains.kotlinx",
          "module": "kotlinx-coroutines-core",
          "version": {
            "requires": "1.3.9",
            "rejects": [
              "_"
            ]
          }
        },
        {
          "group": "org.jetbrains.kotlinx",
          "module": "kotlinx-coroutines-android",
          "version": {
            "requires": "1.3.9",
            "rejects": [
              "_"
            ]
          }
        },
        {
          "group": "androidx.appcompat",
          "module": "appcompat",
          "version": {
            "requires": "1.3.0-alpha01",
            "rejects": [
              "_"
            ]
          }
        },
        {
          "group": "androidx.core",
          "module": "core-ktx",
          "version": {
            "requires": "1.5.0-alpha02",
            "rejects": [
              "_"
            ]
          }
        },
        {
          "group": "androidx.lifecycle",
          "module": "lifecycle-common-java8",
          "version": {
            "requires": "2.3.0-alpha07",
            "rejects": [
              "_"
            ]
          }
        },
        {
          "group": "androidx.lifecycle",
          "module": "lifecycle-runtime-ktx",
          "version": {
            "requires": "2.3.0-alpha07",
            "rejects": [
              "_"
            ]
          }
        },
        {
          "group": "androidx.lifecycle",
          "module": "lifecycle-viewmodel-ktx",
          "version": {
            "requires": "2.3.0-alpha07",
            "rejects": [
              "_"
            ]
          }
        },
        {
          "group": "androidx.lifecycle",
          "module": "lifecycle-livedata-core-ktx",
          "version": {
            "requires": "2.3.0-alpha07",
            "rejects": [
              "_"
            ]
          }
        }
      ],
      "files": [
        {
          "name": "toolkit-preference-runtime-base-0.4.2.aar",
          "url": "toolkit-preference-runtime-base-0.4.2.aar",
          "size": 80825,
          "sha512": "043dce661322d1377a05dc7caebe343b7efc0696129d8062e533e6ae02ad69ebd49c267bb5e7fd02c9fd76a183d1207635f3b9ab140043f3f3427f6dbd803d29",
          "sha256": "41552e5625080c567c5bd0243977fb9894584e91bdab9ca4fb6c98c942d22b88",
          "sha1": "767b8a67c7e94bff048fd0fa512cf7429fa82c99",
          "md5": "9cae510c145d3c55244e3812a4f47c5f"
        }
      ]
    }
  ]
}
